verbaendeliste_bundestag.py
verbaendeliste_bundestag-0.1.0.dist-info/DESCRIPTION.rst
verbaendeliste_bundestag-0.1.0.dist-info/METADATA
verbaendeliste_bundestag-0.1.0.dist-info/pydist.json
verbaendeliste_bundestag-0.1.0.dist-info/RECORD
verbaendeliste_bundestag-0.1.0.dist-info/top_level.txt
verbaendeliste_bundestag-0.1.0.dist-info/WHEEL
