Metadata-Version: 2.0
Name: verbaendeliste-bundestag
Version: 0.1.0
Summary: Parse PDF-to-XML converted lobby list of German Bundestag
Home-page: https://github.com/stefanw/verbaendeliste-bundestag
Author: Stefan Wehrmeyer
Author-email: mail@stefanwehrmeyer.com
License: MIT
Platform: UNKNOWN
Classifier: Development Status :: 4 - Beta
Classifier: Environment :: Console
Classifier: Intended Audience :: Developers
Classifier: License :: OSI Approved :: MIT License
Classifier: Natural Language :: English
Classifier: Operating System :: OS Independent
Classifier: Programming Language :: Python :: 2.7
